aioqiwi/__init__.py
aioqiwi/contrib/__init__.py
aioqiwi/contrib/history_polling.py
aioqiwi/core/__init__.py
aioqiwi/core/connectors/__init__.py
aioqiwi/core/connectors/abstract.py
aioqiwi/core/connectors/aiohttp.py
aioqiwi/core/connectors/asyncio.py
aioqiwi/core/connectors/httpx.py
aioqiwi/core/currencies/__init__.py
aioqiwi/core/currencies/currencies_parsed.py
aioqiwi/core/currencies/currency_utils.py
aioqiwi/core/filter.py
aioqiwi/core/handler.py
aioqiwi/core/requests.py
aioqiwi/core/returns.py
aioqiwi/core/server.py
aioqiwi/core/tooling/__init__.py
aioqiwi/core/tooling/datetime.py
aioqiwi/core/tooling/htstrings.py
aioqiwi/core/tooling/json.py
aioqiwi/core/tooling/phone.py
aioqiwi/exceptions.py
aioqiwi/kassa/__init__.py
aioqiwi/kassa/crypto.py
aioqiwi/kassa/enums.py
aioqiwi/kassa/requests.py
aioqiwi/kassa/server.py
aioqiwi/kassa/types/__init__.py
aioqiwi/kassa/types/invoice.py
aioqiwi/kassa/types/refund.py
aioqiwi/kassa/types/updates.py
aioqiwi/kassa/urls.py
aioqiwi/terminals/__init__.py
aioqiwi/terminals/requests.py
aioqiwi/terminals/types/__init__.py
aioqiwi/terminals/types/partner.py
aioqiwi/terminals/types/polygon.py
aioqiwi/terminals/types/terminal.py
aioqiwi/terminals/urls.py
aioqiwi/types/__init__.py
aioqiwi/types/base.py
aioqiwi/wallet/__init__.py
aioqiwi/wallet/enums.py
aioqiwi/wallet/errors.py
aioqiwi/wallet/requests.py
aioqiwi/wallet/server.py
aioqiwi/wallet/types/__init__.py
aioqiwi/wallet/types/auth_user.py
aioqiwi/wallet/types/balance.py
aioqiwi/wallet/types/commission.py
aioqiwi/wallet/types/history.py
aioqiwi/wallet/types/identification.py
aioqiwi/wallet/types/offer.py
aioqiwi/wallet/types/payment.py
aioqiwi/wallet/types/phone_provider.py
aioqiwi/wallet/types/stats.py
aioqiwi/wallet/types/webhook.py
aioqiwi/wallet/urls.py
aioqiwi-1.1.4.dist-info/LICENSE
aioqiwi-1.1.4.dist-info/WHEEL
aioqiwi-1.1.4.dist-info/METADATA
aioqiwi-1.1.4.dist-info/RECORD
