Metadata-Version: 2.1
Name: aioqiwi
Version: 1.1.4
Summary: Convenient and asynchronous qiwi.com api-wrapper library
Home-page: https://github.com/uwinx/aioqiwi
Keywords: asyncio,aiohttp,qiwi,api-client,aioqiwi
Author: Martin Winks
Author-email: cat@snejugal.ru
Requires-Python: >=3.7,<4.0
Classifier: Programming Language :: Python :: 3
Classifier: Programming Language :: Python :: 3.7
Classifier: Programming Language :: Python :: 3.8
Requires-Dist: aiohttp (>=3.6.2,<4.0.0)
Requires-Dist: pydantic (>=1.4,<2.0)
Project-URL: Repository, https://github.com/uwinx/aioqiwi
